uncolor/__init__.py
uncolor/cli.py
uncolor-0.1.4.dist-info/entry_points.txt
uncolor-0.1.4.dist-info/LICENSE
uncolor-0.1.4.dist-info/WHEEL
uncolor-0.1.4.dist-info/METADATA
uncolor-0.1.4.dist-info/RECORD
