Metadata-Version: 2.1
Name: uncolor
Version: 0.1.4
Summary: strips ANSI colors from a data stream
Home-page: https://pypi.org/project/uncolor
License: Apache 2.0
Author: Ryan Delaney
Author-email: ryan.patrick.delaney+git@protonmail.com
Requires-Python: >=3.7,<4.0
Classifier: Development Status :: 4 - Beta
Classifier: Environment :: Console
Classifier: License :: OSI Approved :: Apache Software License
Classifier: License :: Other/Proprietary License
Classifier: Programming Language :: Python :: 3
Classifier: Programming Language :: Python :: 3.7
Classifier: Programming Language :: Python :: 3.8
Classifier: Programming Language :: Python :: 3.9
Classifier: Programming Language :: Python :: 3.10
Classifier: Programming Language :: Python :: 3.11
Classifier: Programming Language :: Python :: 3 :: Only
Classifier: Programming Language :: Python :: 3.10
Requires-Dist: pytest-datadir (>=1.3.1,<2.0.0)
Project-URL: Repository, https://github.com/rpdelaney/uncolor
